Metadata-Version: 1.0
Name: google-trans-new-tmp
Version: 1.2.2
Summary: A useful module
Home-page: UNKNOWN
Author: Man Foo
Author-email: foomail@foo.com
License: UNKNOWN
Platform: UNKNOWN
